bodo_platform_ipyparallel_kernel/__init__.py
bodo_platform_ipyparallel_kernel/__main__.py
bodo_platform_ipyparallel_kernel/_version.py
bodo_platform_ipyparallel_kernel/helpers.py
bodo_platform_ipyparallel_kernel/install.py
bodo_platform_ipyparallel_kernel/kernel.py
bodo_platform_ipyparallel_kernel/launcher.py
bodo_platform_ipyparallel_kernel/platform_hostfile_update.py
bodo_platform_ipyparallel_kernel/utils.py
bodo_platform_ipyparallel_kernel-2.4.0.dist-info/LICENSE
bodo_platform_ipyparallel_kernel-2.4.0.dist-info/METADATA
bodo_platform_ipyparallel_kernel-2.4.0.dist-info/WHEEL
bodo_platform_ipyparallel_kernel-2.4.0.dist-info/entry_points.txt
bodo_platform_ipyparallel_kernel-2.4.0.dist-info/top_level.txt
bodo_platform_ipyparallel_kernel-2.4.0.dist-info/RECORD
