Metadata-Version: 2.1
Name: bodo-platform-ipyparallel-kernel
Version: 2.4.0
Summary: A simple IPyParallel based wrapper around IPython Kernel for the Bodo Platform
Home-page: https://github.com/Bodo-inc/bodo-platform-ipyparallel-kernel
Author: Bodo, Inc.
Author-email: noreply@bodo.ai
License: UNKNOWN
Platform: UNKNOWN
Classifier: License :: OSI Approved :: BSD License
Classifier: Programming Language :: Python :: 3
License-File: LICENSE
Requires-Dist: jupyter-client (>=7)
Requires-Dist: ipython (>=7)
Requires-Dist: ipykernel (>=6)
Requires-Dist: ipyparallel (>=8)
